LICENSE
scripts/item_data.bz2
wakautosolver/__init__.py
wakautosolver/_build_codes.py
wakautosolver/_compat.py
wakautosolver/_mp_fb.py
wakautosolver/item_conditions.py
wakautosolver/py.typed
wakautosolver/restructured_types.py
wakautosolver/solver.py
wakautosolver/versioned_entrypoints.py
wakautosolver/wakforge_buildcodes.py
wakautosolver/b2048/__init__.py
wakautosolver/b2048/dec_table.py
wakautosolver/b2048/enc_table.py
wakautosolver/b2048/encoder.py
wakautosolver/data/locale_bundle.bz2
wakautosolver/data/readme.md
wakautosolver/data/source_info.xz
wakautosolver/data/stat_only_bundle.xz
wakautosolver-2025.11.1.dist-info/METADATA
wakautosolver-2025.11.1.dist-info/WHEEL
wakautosolver-2025.11.1.dist-info/licenses/LICENSE
wakautosolver-2025.11.1.dist-info/RECORD
