Metadata-Version: 2.3
Name: wakautosolver
Version: 2025.11.1
Project-URL: Homepage, https://github.com/mikeshardmind/wakfu-utils
Author-email: Michael Hall <michael@michaelhall.tech>
License-Expression: MPL-2.0
License-File: LICENSE
Requires-Python: >=3.10
